LICENSE
MANIFEST.in
README.md
setup.py
spswarehouse/__init__.py
spswarehouse/canvas.py
spswarehouse/credentials.py.template
spswarehouse/googledrive.py
spswarehouse/googlesheets.py
spswarehouse/googleslides.py
spswarehouse/magic_spreadsheet.py
spswarehouse/requirements.txt
spswarehouse/table_names.py
spswarehouse/table_utils.py
spswarehouse/warehouse.py
spswarehouse.egg-info/PKG-INFO
spswarehouse.egg-info/SOURCES.txt
spswarehouse.egg-info/dependency_links.txt
spswarehouse.egg-info/top_level.txt
spswarehouse/calpads/__init__.py
spswarehouse/calpads/calpads.py
spswarehouse/calpads/calpads_config.py
spswarehouse/general/__init__.py
spswarehouse/general/os.py
spswarehouse/general/selenium.py
spswarehouse/powerschool/__init__.py
spswarehouse/powerschool/powerschool.py
spswarehouse/powerschool/powerschool_calpads.py
spswarehouse/powerschool/student_passwords.py