Metadata-Version: 2.1
Name: spswarehouse
Version: 0.7.3
Summary: Summit Public Schools Snowflake warehouse
Home-page: https://github.com/SummitPublicSchools/spswarehouse
Author: Summit Public Schools; Harry Li Consulting, LLC
Author-email: warehouse@summitps.org
Classifier: Programming Language :: Python :: 3
License-File: LICENSE
